qps_limit/__init__.py
qps_limit/limiter.py
qps_limit/run.py
qps_limit-1.2.7.dist-info/METADATA
qps_limit-1.2.7.dist-info/WHEEL
qps_limit-1.2.7.dist-info/top_level.txt
qps_limit-1.2.7.dist-info/zip-safe
qps_limit-1.2.7.dist-info/RECORD
